{
    "eventos": [
        {
            "nome": "teste de nome",
            "data": "2023-10-01",
            "tema": "teste de tema",
            "participantes": [
                "João",
                "Maria",
                "Pedro"
            ]
        }
    ],
    "participantes": [
        {
            "cpf": "444.444.444-04",
            "nome": "João",
            "email": "jhonas@gmail.com",
            "preferencias_tematicas": [

            ]
        },
        {
            "cpf": "123.123.123-23",
            "nome": "Sans",
            "email": "sans.sans@gmail.com",
            "preferencias_tematicas": []
        }
    ]
}